src/__init__.py
src/main.py
tests/__init__.py
tests/test_add.py
diego_ci_cd-1.0.4.dist-info/METADATA
diego_ci_cd-1.0.4.dist-info/WHEEL
diego_ci_cd-1.0.4.dist-info/top_level.txt
diego_ci_cd-1.0.4.dist-info/RECORD
