Metadata-Version: 2.4
Name: diego-ci-cd
Version: 1.0.4
Summary: Descripción de tu proyecto
Author: Diego Garcia
Author-email: correoinformatica777@gmail.com
Requires-Dist: pytest
Requires-Dist: flake8
Requires-Dist: setuptools
Dynamic: author
Dynamic: author-email
Dynamic: requires-dist
Dynamic: summary
